{"cameraMode":{"drawMode":0,"name":"Shaded","section":"Shading Mode"},"sceneLighting":true,"audioPlay":false,"sceneViewState":{"m_AlwaysRefresh":false,"showFog":true,"showSkybox":true,"showFlares":true,"showImageEffects":true,"showParticleSystems":true,"showVisualEffectGraphs":true,"m_FxEnabled":true},"in2DMode":false,"pivot":{"x":12.685118675231934,"y":1.3192428350448609,"z":20.396581649780275},"rotation":{"x":0.0771113783121109,"y":-0.7594084739685059,"z":0.09156906604766846,"w":0.6395083665847778},"size":21.0550594329834,"orthographic":false}